mlsdk/__init__.py
mlsdk/client.py
mlsdk/helpers/__init__.py
mlsdk/helpers/langchain.py
mlsdk/helpers/langgraph.py
mlsdk/httpclient.py
mlsdk/queue.py
mlsdk/session.py
mlsdk/types.py
mlsdk/ws.py
mlsdk_python-1.0.4.dist-info/METADATA
mlsdk_python-1.0.4.dist-info/WHEEL
mlsdk_python-1.0.4.dist-info/RECORD
