Metadata-Version: 2.3
Name: mlsdk-python
Version: 1.0.4
Summary: 
Author: Mindlytics
Author-email: info@mindlytics.ai
Requires-Python: >=3.10
Classifier: Programming Language :: Python :: 3
Classifier: Programming Language :: Python :: 3.11
Classifier: Programming Language :: Python :: 3.12
Classifier: Programming Language :: Python :: 3.13
Requires-Dist: aiohttp[speedups] (>=3.11.18,<4.0.0)
Requires-Dist: asyncio (>=3.4.3,<4.0.0)
Requires-Dist: backoff (>=2.2.1,<3.0.0)
Requires-Dist: pydantic (>=2.11.4,<3.0.0)
Requires-Dist: pytest-asyncio (>=0.26.0,<0.27.0)
Requires-Dist: websockets (>=15.0.1,<16.0.0)
